Workbook

Sheet Modelo de Pedido
A1: VANGUARD PEPTIDES — MODELO DE PEDIDO REAL
A2: Baseado no pedido real: 4cx TR15 + 2cx RT15 · R$ 3.200 + R$ 350 FedEx
A4: ⚙ CUSTOS DO PEDIDO | D4: VALOR | F4: NOTA
A5: Frete fixo (USD) | D5: 90 | F5: Valor fixo independente da qtd
A6: Taxa FedEx / importação (R$) | D6: 350 | F6: Declarado como outro produto — varia
A7: Câmbio USD/BRL | D7: 5.2459 | F7: Implícito no pedido real (3200÷610)
A9: Produto | B9: SKU | C9: Qtd Cx | D9: Preço/Cx (USD) | E9: Total (USD) | F9: % custo produtos | G9: Custo Prod. (R$) | H9: Frete alocado (R$) | I9: FedEx alocado (R$) | J9: Custo/Vial (R$) | K9: Preço Venda (R$)
A10: Tirzepatida 15mg | B10: TR15 | C10: 0 | D10: 70 | E10: =C10*D10 -> 0 | F10: =E10/SUM($E$10:$E$19) -> 0 | G10: =E10*$D$7 -> 0 | H10: =($D$5*$D$7)*F10 -> 0 | I10: =$D$6*F10 -> 0 | J10: =IFERROR((G10+H10+I10)/(C10*10),0) -> 0 | K10: 299
A11: Retatrutida 15mg | B11: RT15 | C11: 2 | D11: 120 | E11: =C11*D11 -> 240 | F11: =E11/SUM($E$10:$E$19) -> 0.17790956 | G11: =E11*$D$7 -> 1259.016 | H11: =($D$5*$D$7)*F11 -> 83.99662 | I11: =$D$6*F11 -> 62.268347 | J11: =IFERROR((G11+H11+I11)/(C11*10),0) -> 70.264048 | K11: 399
A12: GHK-Cu 50mg | B12: CU50 | C12: 5 | D12: 35 | E12: =C12*D12 -> 175 | F12: =E12/SUM($E$10:$E$19) -> 0.12972572 | G12: =E12*$D$7 -> 918.0325 | H12: =($D$5*$D$7)*F12 -> 61.247535 | I12: =$D$6*F12 -> 45.404003 | J12: =IFERROR((G12+H12+I12)/(C12*10),0) -> 20.493681 | K12: 299
A13: GLOW Blend 70mg | B13: BBG70 | C13: 2 | D13: 180 | E13: =C13*D13 -> 360 | F13: =E13/SUM($E$10:$E$19) -> 0.26686434 | G13: =E13*$D$7 -> 1888.524 | H13: =($D$5*$D$7)*F13 -> 125.99493 | I13: =$D$6*F13 -> 93.40252 | J13: =IFERROR((G13+H13+I13)/(C13*10),0) -> 105.39607 | K13: 699
A14: SNAP-8 10mg | B14: NP810 | C14: 0 | D14: 50 | E14: =C14*D14 -> 0 | F14: =E14/SUM($E$10:$E$19) -> 0 | G14: =E14*$D$7 -> 0 | H14: =($D$5*$D$7)*F14 -> 0 | I14: =$D$6*F14 -> 0 | J14: =IFERROR((G14+H14+I14)/(C14*10),0) -> 0 | K14: 290
A15: Tesamorelin 10mg | B15: TSM10 | C15: 3 | D15: 160 | E15: =C15*D15 -> 480 | F15: =E15/SUM($E$10:$E$19) -> 0.35581913 | G15: =E15*$D$7 -> 2518.032 | H15: =($D$5*$D$7)*F15 -> 167.99324 | I15: =$D$6*F15 -> 124.53669 | J15: =IFERROR((G15+H15+I15)/(C15*10),0) -> 93.685398 | K15: 520
A16: Epithalon 10mg | B16: ET10 | C16: 0 | D16: 40 | E16: =C16*D16 -> 0 | F16: =E16/SUM($E$10:$E$19) -> 0 | G16: =E16*$D$7 -> 0 | H16: =($D$5*$D$7)*F16 -> 0 | I16: =$D$6*F16 -> 0 | J16: =IFERROR((G16+H16+I16)/(C16*10),0) -> 0 | K16: 249
A17: PT-141 10mg | B17: P41 | C17: 1 | D17: 50 | E17: =C17*D17 -> 50 | F17: =E17/SUM($E$10:$E$19) -> 0.037064492 | G17: =E17*$D$7 -> 262.295 | H17: =($D$5*$D$7)*F17 -> 17.499296 | I17: =$D$6*F17 -> 12.972572 | J17: =IFERROR((G17+H17+I17)/(C17*10),0) -> 29.276687 | K17: 280
A18: bac.water | B18: BA03 | C18: 0 | D18: 10 | E18: =C18*D18 -> 0 | F18: =E18/SUM($E$10:$E$19) -> 0 | G18: =E18*$D$7 -> 0 | H18: =($D$5*$D$7)*F18 -> 0 | I18: =$D$6*F18 -> 0 | J18: =IFERROR((G18+H18+I18)/(C18*10),0) -> 0 | K18: 0
A19: Selank 5mg | B19: SK5 | C19: 1 | D19: 44 | E19: =C19*D19 -> 44 | F19: =E19/SUM($E$10:$E$19) -> 0.032616753 | G19: =E19*$D$7 -> 230.8196 | H19: =($D$5*$D$7)*F19 -> 15.39938 | I19: =$D$6*F19 -> 11.415864 | J19: =IFERROR((G19+H19+I19)/(C19*10),0) -> 25.763484 | K19: 199
A20: TOTAIS DO PEDIDO | C20: =SUM(C10:C19) -> 14 | E20: =SUM(E10:E19) -> 1349 | F20: =SUM(F10:F19) -> 1 | G20: =SUM(G10:G19) -> 7076.7191 | H20: =SUM(H10:H19) -> 472.131 | I20: =SUM(I10:I19) -> 350 | J20: =(SUM(G10:I19)+E5*E7+E6)/SUM(C10:C19)/10 -> 56.420358
A22: Produto | B22: SKU | C22: Qtd Cx | D22: Preço/Cx (USD) | E22: Total (USD) | F22: % custo produtos | G22: Custo Prod. (R$) | H22: Frete alocado (R$) | I22: FedEx alocado (R$) | J22: Custo/Vial (R$) | K22: Preço Venda (R$)
A23: bac.water | B23: BA03 | C23: =C20 -> 14 | D23: 10 | E23: =C23*D23 -> 140 | F23: =E23/SUM($E$23) -> 1 | G23: =E23*$D$7 -> 734.426 | H23: =($D$5*$D$7)*F23 -> 472.131 | I23: =$D$6*F23 -> 350 | J23: =IFERROR((G23+H23+I23)/(C23*10),0) -> 11.118264 | K23: 0
A24: TOTAIS DO PEDIDO | C24: =SUM(C23) -> 14 | E24: =SUM(E14:E23) -> 2063 | F24: =SUM(F23) -> 1 | G24: =SUM(G23) -> 734.426 | H24: =SUM(H14:H23) -> 1145.1539 | I24: =SUM(I14:I23) -> 848.92513 | J24: =(SUM(G23:I23)+D5*D7+D6)/SUM(C23)/10 -> 16.990629
A29: Produto | B29: Custo/Vial (R$) | C29: Preço Venda (R$) | D29: Margem Bruta (R$) | E29: Markup (%) | F29: Margem (%) | G29: Status
A30: Tirzepatida 15mg | B30: =IFERROR(J10,0) -> 0 | C30: =K10 -> 299 | D30: =C30-B30 -> 299 | E30: =IFERROR(C30/B30-1,0) -> 0 | F30: =IFERROR(D30/C30,0) -> 1 | G30: =IF(F30>=0.7,"🚀 Excelente",IF(F30>=0.5,"✅ Ótima",IF(F30>=0.35,"⚠ Boa","🔴 Baixa"))) -> 🚀 Excelente
A31: Retatrutida 15mg | B31: =IFERROR(J11,0) -> 70.264048 | C31: =K11 -> 399 | D31: =C31-B31 -> 328.73595 | E31: =IFERROR(C31/B31-1,0) -> 4.6785797 | F31: =IFERROR(D31/C31,0) -> 0.82389963 | G31: =IF(F31>=0.7,"🚀 Excelente",IF(F31>=0.5,"✅ Ótima",IF(F31>=0.35,"⚠ Boa","🔴 Baixa"))) -> 🚀 Excelente
A32: GHK-Cu 50mg | B32: =IFERROR(J12,0) -> 20.493681 | C32: =K12 -> 299 | D32: =C32-B32 -> 278.50632 | E32: =IFERROR(C32/B32-1,0) -> 13.589863 | F32: =IFERROR(D32/C32,0) -> 0.93145926 | G32: =IF(F32>=0.7,"🚀 Excelente",IF(F32>=0.5,"✅ Ótima",IF(F32>=0.35,"⚠ Boa","🔴 Baixa"))) -> 🚀 Excelente
A33: GLOW Blend 70mg | B33: =IFERROR(J13,0) -> 105.39607 | C33: =K13 -> 699 | D33: =C33-B33 -> 593.60393 | E33: =IFERROR(C33/B33-1,0) -> 5.6321257 | F33: =IFERROR(D33/C33,0) -> 0.84921878 | G33: =IF(F33>=0.7,"🚀 Excelente",IF(F33>=0.5,"✅ Ótima",IF(F33>=0.35,"⚠ Boa","🔴 Baixa"))) -> 🚀 Excelente
A34: SNAP-8 10mg | B34: =IFERROR(J14,0) -> 0 | C34: =K14 -> 290 | D34: =C34-B34 -> 290 | E34: =IFERROR(C34/B34-1,0) -> 0 | F34: =IFERROR(D34/C34,0) -> 1 | G34: =IF(F34>=0.7,"🚀 Excelente",IF(F34>=0.5,"✅ Ótima",IF(F34>=0.35,"⚠ Boa","🔴 Baixa"))) -> 🚀 Excelente
A35: Tesamorelin 10mg | B35: =IFERROR(J15,0) -> 93.685398 | C35: =K15 -> 520 | D35: =C35-B35 -> 426.3146 | E35: =IFERROR(C35/B35-1,0) -> 4.5504915 | F35: =IFERROR(D35/C35,0) -> 0.81983577 | G35: =IF(F35>=0.7,"🚀 Excelente",IF(F35>=0.5,"✅ Ótima",IF(F35>=0.35,"⚠ Boa","🔴 Baixa"))) -> 🚀 Excelente
A36: Epithalon 10mg | B36: =IFERROR(J16,0) -> 0 | C36: =K16 -> 249 | D36: =C36-B36 -> 249 | E36: =IFERROR(C36/B36-1,0) -> 0 | F36: =IFERROR(D36/C36,0) -> 1 | G36: =IF(F36>=0.7,"🚀 Excelente",IF(F36>=0.5,"✅ Ótima",IF(F36>=0.35,"⚠ Boa","🔴 Baixa"))) -> 🚀 Excelente
A37: PT-141 10mg | B37: =IFERROR(J17,0) -> 29.276687 | C37: =K17 -> 280 | D37: =C37-B37 -> 250.72331 | E37: =IFERROR(C37/B37-1,0) -> 8.5639237 | F37: =IFERROR(D37/C37,0) -> 0.8954404 | G37: =IF(F37>=0.7,"🚀 Excelente",IF(F37>=0.5,"✅ Ótima",IF(F37>=0.35,"⚠ Boa","🔴 Baixa"))) -> 🚀 Excelente
A38: Selank 5mg | B38: =IFERROR(J19,0) -> 25.763484 | C38: =K19 -> 199 | D38: =C38-B38 -> 173.23652 | E38: =IFERROR(C38/B38-1,0) -> 6.7241105 | F38: =IFERROR(D38/C38,0) -> 0.87053525 | G38: =IF(F38>=0.7,"🚀 Excelente",IF(F38>=0.5,"✅ Ótima",IF(F38>=0.35,"⚠ Boa","🔴 Baixa"))) -> 🚀 Excelente
A40: 💰 SIMULADOR — FATURAMENTO MÍNIMO PARA QUITAR O PEDIDO
A41: Tirzepatida 15mg | B41: 40 vials disponíveis | C41: =IFERROR(J10*C10*10,0) -> 0 | D41: ← custo total do estoque | E41: =K10*C10*10 -> 0 | F41: ← receita se vender tudo | G41: =IFERROR(ROUNDUP(J10*C10*10/K10,0),0) -> 0 | H41: vials para pagar o pedido
A42: Retatrutida 15mg | B42: 40 vials disponíveis | C42: =IFERROR(J11*C11*10,0) -> 1405.281 | D42: ← custo total do estoque | E42: =K11*C11*10 -> 7980 | F42: ← receita se vender tudo | G42: =IFERROR(ROUNDUP(J11*C11*10/K11,0),0) -> 4 | H42: vials para pagar o pedido
A43: GHK-Cu 50mg | B43: 40 vials disponíveis | C43: =IFERROR(J12*C12*10,0) -> 1024.684 | D43: ← custo total do estoque | E43: =K12*C12*10 -> 14950 | F43: ← receita se vender tudo | G43: =IFERROR(ROUNDUP(J12*C12*10/K12,0),0) -> 4 | H43: vials para pagar o pedido
A44: GLOW Blend 70mg | B44: 40 vials disponíveis | C44: =IFERROR(J13*C13*10,0) -> 2107.9214 | D44: ← custo total do estoque | E44: =K13*C13*10 -> 13980 | F44: ← receita se vender tudo | G44: =IFERROR(ROUNDUP(J13*C13*10/K13,0),0) -> 4 | H44: vials para pagar o pedido
A45: SNAP-8 10mg | B45: 40 vials disponíveis | C45: =IFERROR(J14*C14*10,0) -> 0 | D45: ← custo total do estoque | E45: =K14*C14*10 -> 0 | F45: ← receita se vender tudo | G45: =IFERROR(ROUNDUP(J14*C14*10/K14,0),0) -> 0 | H45: vials para pagar o pedido
A46: Tesamorelin 5mg | B46: 40 vials disponíveis | C46: =IFERROR(J15*C15*10,0) -> 2810.5619 | D46: ← custo total do estoque | E46: =K15*C15*10 -> 15600 | F46: ← receita se vender tudo | G46: =IFERROR(ROUNDUP(J15*C15*10/K15,0),0) -> 6 | H46: vials para pagar o pedido
A47: Epithalon 10mg | B47: 40 vials disponíveis | C47: =IFERROR(J16*C16*10,0) -> 0 | D47: ← custo total do estoque | E47: =K16*C16*10 -> 0 | F47: ← receita se vender tudo | G47: =IFERROR(ROUNDUP(J16*C16*10/K16,0),0) -> 0 | H47: vials para pagar o pedido
A48: PT-141 10mg | B48: 40 vials disponíveis | C48: =IFERROR(J17*C17*10,0) -> 292.76687 | D48: ← custo total do estoque | E48: =K17*C17*10 -> 2800 | F48: ← receita se vender tudo | G48: =IFERROR(ROUNDUP(J17*C17*10/K17,0),0) -> 2 | H48: vials para pagar o pedido
A49: Selank 5mg | B49: 40 vials disponíveis | C49: =IFERROR(J19*C19*10,0) -> 257.63484 | D49: ← custo total do estoque | E49: =K19*C19*10 -> 1990 | F49: ← receita se vender tudo | G49: =IFERROR(ROUNDUP(J19*C19*10/K19,0),0) -> 2 | H49: vials para pagar o pedido
A50: TOTAIS DO PEDIDO | C50: =SUM(C41:C49) -> 7898.8501 | E50: =SUM(E41:E49) -> 57300

Sheet Portfólio — Margem Real
A1: PORTFÓLIO VANGUARD — CUSTO REAL (COM FRETE E FEDEX)
A2: Custo/vial = produto + frete+fedex rateado · câmbio linkado da aba Modelo de Pedido
A4: ⚙ PARÂMETROS GLOBAIS
A5: Câmbio USD/BRL | C5: 5.8
A6: Frete fixo (USD) por pedido | C6: 90
A7: Taxa FedEx estimada (R$) | C7: 350
A8: Qtd mínima de caixas/pedido | C8: 9
A10: Produto | B10: SKU Forn. | C10: Preço/Cx (USD) | D10: Custo Prod. /vial (R$) | E10: Custo c/ Overhead /vial (R$) | F10: Preço Venda (R$) | G10: Margem Bruta (R$) | H10: Markup (%) | I10: Margem (%) | J10: Status
A11: Tirzepatida 15mg | B11: TR15 | C11: 70 | D11: =C11/10*$C$5 -> 40.6 | E11: =D11+($C$6*$C$5+$C$7)/$C$8/10 -> 50.288889 | F11: 299 | G11: =F11-E11 -> 248.71111 | H11: =IFERROR(F11/E11-1,0) -> 4.9456474 | I11: =G11/F11 -> 0.83180974 | J11: =IF(I11>=0.7,"🚀 Excelente",IF(I11>=0.5,"✅ Ótima",IF(I11>=0.35,"⚠ Boa","🔴 Baixa"))) -> 🚀 Excelente
A12: Retatrutida 15mg | B12: RT15 | C12: 120 | D12: =C12/10*$C$5 -> 69.6 | E12: =D12+($C$6*$C$5+$C$7)/$C$8/10 -> 79.288889 | F12: 399 | G12: =F12-E12 -> 319.71111 | H12: =IFERROR(F12/E12-1,0) -> 4.0322309 | I12: =G12/F12 -> 0.80128098 | J12: =IF(I12>=0.7,"🚀 Excelente",IF(I12>=0.5,"✅ Ótima",IF(I12>=0.35,"⚠ Boa","🔴 Baixa"))) -> 🚀 Excelente
A13: GHK-Cu 50mg | B13: CU50 | C13: 35 | D13: =C13/10*$C$5 -> 20.3 | E13: =D13+($C$6*$C$5+$C$7)/$C$8/10 -> 29.988889 | F13: 299 | G13: =F13-E13 -> 269.01111 | H13: =IFERROR(F13/E13-1,0) -> 8.9703594 | I13: =G13/F13 -> 0.89970271 | J13: =IF(I13>=0.7,"🚀 Excelente",IF(I13>=0.5,"✅ Ótima",IF(I13>=0.35,"⚠ Boa","🔴 Baixa"))) -> 🚀 Excelente
A14: GLOW Blend 70mg | B14: BBG70 | C14: 180 | D14: =C14/10*$C$5 -> 104.4 | E14: =D14+($C$6*$C$5+$C$7)/$C$8/10 -> 114.08889 | F14: 699 | G14: =F14-E14 -> 584.91111 | H14: =IFERROR(F14/E14-1,0) -> 5.1268017 | I14: =G14/F14 -> 0.83678271 | J14: =IF(I14>=0.7,"🚀 Excelente",IF(I14>=0.5,"✅ Ótima",IF(I14>=0.35,"⚠ Boa","🔴 Baixa"))) -> 🚀 Excelente
A15: SNAP-8 10mg | B15: NP810 | C15: 50 | D15: =C15/10*$C$5 -> 29 | E15: =D15+($C$6*$C$5+$C$7)/$C$8/10 -> 38.688889 | F15: 290 | G15: =F15-E15 -> 251.31111 | H15: =IFERROR(F15/E15-1,0) -> 6.4956921 | I15: =G15/F15 -> 0.86659004 | J15: =IF(I15>=0.7,"🚀 Excelente",IF(I15>=0.5,"✅ Ótima",IF(I15>=0.35,"⚠ Boa","🔴 Baixa"))) -> 🚀 Excelente
A16: Tesamorelin 5mg | B16: TSM5 | C16: 100 | D16: =C16/10*$C$5 -> 58 | E16: =D16+($C$6*$C$5+$C$7)/$C$8/10 -> 67.688889 | F16: 299 | G16: =F16-E16 -> 231.31111 | H16: =IFERROR(F16/E16-1,0) -> 3.4172685 | I16: =G16/F16 -> 0.77361576 | J16: =IF(I16>=0.7,"🚀 Excelente",IF(I16>=0.5,"✅ Ótima",IF(I16>=0.35,"⚠ Boa","🔴 Baixa"))) -> 🚀 Excelente
A17: Epithalon 10mg | B17: ET10 | C17: 40 | D17: =C17/10*$C$5 -> 23.2 | E17: =D17+($C$6*$C$5+$C$7)/$C$8/10 -> 32.888889 | F17: 249 | G17: =F17-E17 -> 216.11111 | H17: =IFERROR(F17/E17-1,0) -> 6.5709459 | I17: =G17/F17 -> 0.86791611 | J17: =IF(I17>=0.7,"🚀 Excelente",IF(I17>=0.5,"✅ Ótima",IF(I17>=0.35,"⚠ Boa","🔴 Baixa"))) -> 🚀 Excelente
A18: PT-141 10mg | B18: P41 | C18: 50 | D18: =C18/10*$C$5 -> 29 | E18: =D18+($C$6*$C$5+$C$7)/$C$8/10 -> 38.688889 | F18: 280 | G18: =F18-E18 -> 241.31111 | H18: =IFERROR(F18/E18-1,0) -> 6.23722 | I18: =G18/F18 -> 0.8618254 | J18: =IF(I18>=0.7,"🚀 Excelente",IF(I18>=0.5,"✅ Ótima",IF(I18>=0.35,"⚠ Boa","🔴 Baixa"))) -> 🚀 Excelente
A19: Selank 5mg | B19: SK5 | C19: 44 | D19: =C19/10*$C$5 -> 25.52 | E19: =D19+($C$6*$C$5+$C$7)/$C$8/10 -> 35.208889 | F19: 199 | G19: =F19-E19 -> 163.79111 | H19: =IFERROR(F19/E19-1,0) -> 4.6519818 | I19: =G19/F19 -> 0.82307091 | J19: =IF(I19>=0.7,"🚀 Excelente",IF(I19>=0.5,"✅ Ótima",IF(I19>=0.35,"⚠ Boa","🔴 Baixa"))) -> 🚀 Excelente

Sheet Catálogo Adina
A1: CATÁLOGO ADINA — TODOS OS PRODUTOS
A3: Peptídeo | B3: Cat. No. | C3: Especificação | D3: Preço Cx (USD) | E3: Custo/Vial (USD) | F3: Custo/Vial (R$) | G3: No catálogo?
A4: Semaglutide | B4: SM2 | C4: 2mg | D4: 28 | E4: =D4/10 -> 2.8 | F4: =E4*'Portfólio — Margem Real'!$C$5 -> 16.24
A5: Semaglutide | B5: SM5 | C5: 5mg | D5: 38 | E5: =D5/10 -> 3.8 | F5: =E5*'Portfólio — Margem Real'!$C$5 -> 22.04
A6: Semaglutide | B6: SM10 | C6: 10mg | D6: 55 | E6: =D6/10 -> 5.5 | F6: =E6*'Portfólio — Margem Real'!$C$5 -> 31.9
A7: Semaglutide | B7: SM15 | C7: 15mg | D7: 65 | E7: =D7/10 -> 6.5 | F7: =E7*'Portfólio — Margem Real'!$C$5 -> 37.7
A8: Semaglutide | B8: SM20 | C8: 20mg | D8: 75 | E8: =D8/10 -> 7.5 | F8: =E8*'Portfólio — Margem Real'!$C$5 -> 43.5
A9: Semaglutide | B9: SM30 | C9: 30mg | D9: 90 | E9: =D9/10 -> 9 | F9: =E9*'Portfólio — Margem Real'!$C$5 -> 52.2
A10: Tirzepatide | B10: TR5 | C10: 5mg | D10: 40 | E10: =D10/10 -> 4 | F10: =E10*'Portfólio — Margem Real'!$C$5 -> 23.2
A11: Tirzepatide | B11: TR10 | C11: 10mg | D11: 55 | E11: =D11/10 -> 5.5 | F11: =E11*'Portfólio — Margem Real'!$C$5 -> 31.9
A12: Tirzepatide | B12: TR15 | C12: 15mg | D12: 70 | E12: =D12/10 -> 7 | F12: =E12*'Portfólio — Margem Real'!$C$5 -> 40.6 | G12: ✅ Sim
A13: Tirzepatide | B13: TR20 | C13: 20mg | D13: 85 | E13: =D13/10 -> 8.5 | F13: =E13*'Portfólio — Margem Real'!$C$5 -> 49.3
A14: Tirzepatide | B14: TR30 | C14: 30mg | D14: 100 | E14: =D14/10 -> 10 | F14: =E14*'Portfólio — Margem Real'!$C$5 -> 58
A15: Tirzepatide | B15: TR40 | C15: 40mg | D15: 120 | E15: =D15/10 -> 12 | F15: =E15*'Portfólio — Margem Real'!$C$5 -> 69.6
A16: Tirzepatide | B16: TR50 | C16: 50mg | D16: 140 | E16: =D16/10 -> 14 | F16: =E16*'Portfólio — Margem Real'!$C$5 -> 81.2
A17: Tirzepatide | B17: TR60 | C17: 60mg | D17: 160 | E17: =D17/10 -> 16 | F17: =E17*'Portfólio — Margem Real'!$C$5 -> 92.8
A18: Tirzepatide | B18: TR100 | C18: 100mg | D18: 240 | E18: =D18/10 -> 24 | F18: =E18*'Portfólio — Margem Real'!$C$5 -> 139.2
A19: Retatrutide | B19: RT5 | C19: 5mg | D19: 50 | E19: =D19/10 -> 5 | F19: =E19*'Portfólio — Margem Real'!$C$5 -> 29
A20: Retatrutide | B20: RT10 | C20: 10mg | D20: 90 | E20: =D20/10 -> 9 | F20: =E20*'Portfólio — Margem Real'!$C$5 -> 52.2
A21: Retatrutide | B21: RT15 | C21: 15mg | D21: 120 | E21: =D21/10 -> 12 | F21: =E21*'Portfólio — Margem Real'!$C$5 -> 69.6 | G21: ✅ Sim
A22: Retatrutide | B22: RT20 | C22: 20mg | D22: 150 | E22: =D22/10 -> 15 | F22: =E22*'Portfólio — Margem Real'!$C$5 -> 87
A23: Retatrutide | B23: RT30 | C23: 30mg | D23: 185 | E23: =D23/10 -> 18.5 | F23: =E23*'Portfólio — Margem Real'!$C$5 -> 107.3
A24: Retatrutide | B24: RT40 | C24: 40mg | D24: 235 | E24: =D24/10 -> 23.5 | F24: =E24*'Portfólio — Margem Real'!$C$5 -> 136.3
A25: Retatrutide | B25: RT50 | C25: 50mg | D25: 285 | E25: =D25/10 -> 28.5 | F25: =E25*'Portfólio — Margem Real'!$C$5 -> 165.3
A26: Retatrutide | B26: RT60 | C26: 60mg | D26: 320 | E26: =D26/10 -> 32 | F26: =E26*'Portfólio — Margem Real'!$C$5 -> 185.6
A27: HGH 191AA | B27: H10 | C27: 10iu | D27: 48 | E27: =D27/10 -> 4.8 | F27: =E27*'Portfólio — Margem Real'!$C$5 -> 27.84
A28: HGH 191AA | B28: H12 | C28: 12iu | D28: 55 | E28: =D28/10 -> 5.5 | F28: =E28*'Portfólio — Margem Real'!$C$5 -> 31.9
A29: HGH 191AA | B29: H15 | C29: 15iu | D29: 68 | E29: =D29/10 -> 6.8 | F29: =E29*'Portfólio — Margem Real'!$C$5 -> 39.44
A30: HGH 191AA | B30: H24 | C30: 24iu | D30: 100 | E30: =D30/10 -> 10 | F30: =E30*'Portfólio — Margem Real'!$C$5 -> 58
A31: HGH 191AA | B31: H36 | C31: 36iu | D31: 150 | E31: =D31/10 -> 15 | F31: =E31*'Portfólio — Margem Real'!$C$5 -> 87
A32: MT-1 | B32: MT1 | C32: 10mg | D32: 45 | E32: =D32/10 -> 4.5 | F32: =E32*'Portfólio — Margem Real'!$C$5 -> 26.1
A33: MT-2 Melanotan | B33: ML10 | C33: 10mg | D33: 45 | E33: =D33/10 -> 4.5 | F33: =E33*'Portfólio — Margem Real'!$C$5 -> 26.1
A34: PT-141 | B34: P41 | C34: 10mg | D34: 50 | E34: =D34/10 -> 5 | F34: =E34*'Portfólio — Margem Real'!$C$5 -> 29 | G34: ✅ Sim
A35: Gonadorelin | B35: GND2 | C35: 2mg | D35: 40 | E35: =D35/10 -> 4 | F35: =E35*'Portfólio — Margem Real'!$C$5 -> 23.2
A36: DSIP | B36: DS5 | C36: 5mg | D36: 40 | E36: =D36/10 -> 4 | F36: =E36*'Portfólio — Margem Real'!$C$5 -> 23.2
A37: DSIP | B37: DS10 | C37: 10mg | D37: 75 | E37: =D37/10 -> 7.5 | F37: =E37*'Portfólio — Margem Real'!$C$5 -> 43.5
A38: DSIP | B38: DS15 | C38: 15mg | D38: 105 | E38: =D38/10 -> 10.5 | F38: =E38*'Portfólio — Margem Real'!$C$5 -> 60.9
A39: Selank | B39: SK5 | C39: 5mg | D39: 44 | E39: =D39/10 -> 4.4 | F39: =E39*'Portfólio — Margem Real'!$C$5 -> 25.52 | G39: ✅ Sim
A40: Selank | B40: SK10 | C40: 10mg | D40: 70 | E40: =D40/10 -> 7 | F40: =E40*'Portfólio — Margem Real'!$C$5 -> 40.6
A41: Selank | B41: SK30 | C41: 30mg | D41: 105 | E41: =D41/10 -> 10.5 | F41: =E41*'Portfólio — Margem Real'!$C$5 -> 60.9
A42: NA Selank Amidate | B42: NSK30 | C42: 30mg | D42: 150 | E42: =D42/10 -> 15 | F42: =E42*'Portfólio — Margem Real'!$C$5 -> 87
A43: Oxytocin | B43: OT2 | C43: 2mg | D43: 30 | E43: =D43/10 -> 3 | F43: =E43*'Portfólio — Margem Real'!$C$5 -> 17.4
A44: Oxytocin | B44: OT5 | C44: 5mg | D44: 60 | E44: =D44/10 -> 6 | F44: =E44*'Portfólio — Margem Real'!$C$5 -> 34.8
A45: Oxytocin | B45: OT10 | C45: 10mg | D45: 90 | E45: =D45/10 -> 9 | F45: =E45*'Portfólio — Margem Real'!$C$5 -> 52.2
A46: Epithalon | B46: ET10 | C46: 10mg | D46: 40 | E46: =D46/10 -> 4 | F46: =E46*'Portfólio — Margem Real'!$C$5 -> 23.2 | G46: ✅ Sim
A47: Epithalon | B47: ET40 | C47: 40mg | D47: 110 | E47: =D47/10 -> 11 | F47: =E47*'Portfólio — Margem Real'!$C$5 -> 63.8
A48: Epithalon | B48: ET50 | C48: 50mg | D48: 140 | E48: =D48/10 -> 14 | F48: =E48*'Portfólio — Margem Real'!$C$5 -> 81.2
A49: BPC-157 | B49: BC5 | C49: 5mg | D49: 45 | E49: =D49/10 -> 4.5 | F49: =E49*'Portfólio — Margem Real'!$C$5 -> 26.1
A50: BPC-157 | B50: BC10 | C50: 10mg | D50: 68 | E50: =D50/10 -> 6.8 | F50: =E50*'Portfólio — Margem Real'!$C$5 -> 39.44
A51: BPC-157 | B51: BC20 | C51: 20mg | D51: 100 | E51: =D51/10 -> 10 | F51: =E51*'Portfólio — Margem Real'!$C$5 -> 58
A52: BPC 5mg + TB 5mg | B52: BB10 | C52: 10mg | D52: 98 | E52: =D52/10 -> 9.8 | F52: =E52*'Portfólio — Margem Real'!$C$5 -> 56.84
A53: BPC 10mg + TB 10mg | B53: BB20 | C53: 20mg | D53: 160 | E53: =D53/10 -> 16 | F53: =E53*'Portfólio — Margem Real'!$C$5 -> 92.8
A54: ACE-031 | B54: AE1 | C54: 1mg | D54: 50 | E54: =D54/10 -> 5 | F54: =E54*'Portfólio — Margem Real'!$C$5 -> 29
A55: AICAR | B55: AR50 | C55: 50mg | D55: 55 | E55: =D55/10 -> 5.5 | F55: =E55*'Portfólio — Margem Real'!$C$5 -> 31.9
A56: AICAR | B56: AR100 | C56: 100mg | D56: 105 | E56: =D56/10 -> 10.5 | F56: =E56*'Portfólio — Margem Real'!$C$5 -> 60.9
A57: Adipotide | B57: AP2 | C57: 2mg | D57: 70 | E57: =D57/10 -> 7 | F57: =E57*'Portfólio — Margem Real'!$C$5 -> 40.6
A58: Adipotide | B58: AP5 | C58: 5mg | D58: 130 | E58: =D58/10 -> 13 | F58: =E58*'Portfólio — Margem Real'!$C$5 -> 75.4
... A90: IGF-1LR3 | B90: IG1 | C90: 1mg | D90: 170 | E90: =D90/10 -> 17 | F90: =E90*'Portfólio — Margem Real'!$C$5 -> 98.6
A91: Tesamorelin | B91: TSM5 | C91: 5mg | D91: 100 | E91: =D91/10 -> 10 | F91: =E91*'Portfólio — Margem Real'!$C$5 -> 58 | G91: ✅ Sim
A92: Tesamorelin | B92: TSM10 | C92: 10mg | D92: 160 | E92: =D92/10 -> 16 | F92: =E92*'Portfólio — Margem Real'!$C$5 -> 92.8
A93: Tesamorelin | B93: TSM20 | C93: 20mg | D93: 280 | E93: =D93/10 -> 28 | F93: =E93*'Portfólio — Margem Real'!$C$5 -> 162.4
A94: Ipamorelin | B94: IP5 | C94: 5mg | D94: 40 | E94: =D94/10 -> 4 | F94: =E94*'Portfólio — Margem Real'!$C$5 -> 23.2
A95: Ipamorelin | B95: IP10 | C95: 10mg | D95: 60 | E95: =D95/10 -> 6 | F95: =E95*'Portfólio — Margem Real'!$C$5 -> 34.8
A96: Hexarelin | B96: HX2 | C96: 2mg | D96: 42 | E96: =D96/10 -> 4.2 | F96: =E96*'Portfólio — Margem Real'!$C$5 -> 24.36
A97: Hexarelin | B97: HX5 | C97: 5mg | D97: 75 | E97: =D97/10 -> 7.5 | F97: =E97*'Portfólio — Margem Real'!$C$5 -> 43.5
A98: Hexarelin | B98: HX10 | C98: 10mg | D98: 150 | E98: =D98/10 -> 15 | F98: =E98*'Portfólio — Margem Real'!$C$5 -> 87
A99: GHK-Cu | B99: CU50 | C99: 50mg | D99: 35 | E99: =D99/10 -> 3.5 | F99: =E99*'Portfólio — Margem Real'!$C$5 -> 20.3 | G99: ✅ Sim
A100: GHK-Cu | B100: CU100 | C100: 100mg | D100: 60 | E100: =D100/10 -> 6 | F100: =E100*'Portfólio — Margem Real'!$C$5 -> 34.8
A101: GHK Basic | B101: GH50 | C101: 50mg | D101: 50 | E101: =D101/10 -> 5 | F101: =E101*'Portfólio — Margem Real'!$C$5 -> 29
A102: AHK-CU | B102: AU100 | C102: 100mg | D102: 75 | E102: =D102/10 -> 7.5 | F102: =E102*'Portfólio — Margem Real'!$C$5 -> 43.5
A103: KissPeptin-10 | B103: KS5 | C103: 5mg | D103: 55 | E103: =D103/10 -> 5.5 | F103: =E103*'Portfólio — Margem Real'!$C$5 -> 31.9
A104: KissPeptin-10 | B104: KS10 | C104: 10mg | D104: 90 | E104: =D104/10 -> 9 | F104: =E104*'Portfólio — Margem Real'!$C$5 -> 52.2
A105: Thymalin | B105: TY10 | C105: 10mg | D105: 65 | E105: =D105/10 -> 6.5 | F105: =E105*'Portfólio — Margem Real'!$C$5 -> 37.7
A106: Thymosin Alpha-1 | B106: TA5 | C106: 5mg | D106: 85 | E106: =D106/10 -> 8.5 | F106: =E106*'Portfólio — Margem Real'!$C$5 -> 49.3
A107: Thymosin Alpha-1 | B107: TA10 | C107: 10mg | D107: 135 | E107: =D107/10 -> 13.5 | F107: =E107*'Portfólio — Margem Real'!$C$5 -> 78.3
A108: MOTS-c | B108: MS10 | C108: 10mg | D108: 60 | E108: =D108/10 -> 6 | F108: =E108*'Portfólio — Margem Real'!$C$5 -> 34.8
A109: MOTS-c | B109: MS40 | C109: 40mg | D109: 165 | E109: =D109/10 -> 16.5 | F109: =E109*'Portfólio — Margem Real'!$C$5 -> 95.7
A110: FOXO4 | B110: F410 | C110: 10mg | D110: 280 | E110: =D110/10 -> 28 | F110: =E110*'Portfólio — Margem Real'!$C$5 -> 162.4
A111: LL37 | B111: LL37 | C111: 5mg | D111: 80 | E111: =D111/10 -> 8 | F111: =E111*'Portfólio — Margem Real'!$C$5 -> 46.4
... A124: Ara-290 | B124: RA10 | C124: 10mg | D124: 63 | E124: =D124/10 -> 6.3 | F124: =E124*'Portfólio — Margem Real'!$C$5 -> 36.54
A125: SNAP-8 | B125: NP810 | C125: 10mg | D125: 50 | E125: =D125/10 -> 5 | F125: =E125*'Portfólio — Margem Real'!$C$5 -> 29 | G125: ✅ Sim
A126: Mazdutide | B126: MDT5 | C126: 5mg | D126: 100 | E126: =D126/10 -> 10 | F126: =E126*'Portfólio — Margem Real'!$C$5 -> 58
A127: Mazdutide | B127: MDT10 | C127: 10mg | D127: 150 | E127: =D127/10 -> 15 | F127: =E127*'Portfólio — Margem Real'!$C$5 -> 87
A128: NAD+ | B128: NJ3100 | C128: 100mg | D128: 50 | E128: =D128/10 -> 5 | F128: =E128*'Portfólio — Margem Real'!$C$5 -> 29
A129: NAD+ | B129: NJ500 | C129: 500mg | D129: 90 | E129: =D129/10 -> 9 | F129: =E129*'Portfólio — Margem Real'!$C$5 -> 52.2
A130: NAD+ | B130: NJ1000 | C130: 1000mg | D130: 160 | E130: =D130/10 -> 16 | F130: =E130*'Portfólio — Margem Real'!$C$5 -> 92.8
A131: BPC+GHK-Cu+TB-500 Blend | B131: BBG70 | C131: 70mg | D131: 180 | E131: =D131/10 -> 18 | F131: =E131*'Portfólio — Margem Real'!$C$5 -> 104.4 | G131: ✅ Sim
A132: Survodutide | B132: SUR10 | C132: 10mg | D132: 260 | E132: =D132/10 -> 26 | F132: =E132*'Portfólio — Margem Real'!$C$5 -> 150.8
A133: Cagrilintide+Semaglutide | B133: CS10 | C133: 10mg | D133: 150 | E133: =D133/10 -> 15 | F133: =E133*'Portfólio — Margem Real'!$C$5 -> 87
A134: Retatrutide+Cagrilintide | B134: RC10 | C134: 10mg | D134: 170 | E134: =D134/10 -> 17 | F134: =E134*'Portfólio — Margem Real'!$C$5 -> 98.6
A135: VIP | B135: VP5 | C135: 5mg | D135: 100 | E135: =D135/10 -> 10 | F135: =E135*'Portfólio — Margem Real'!$C$5 -> 58
A136: VIP | B136: VP10 | C136: 10mg | D136: 150 | E136: =D136/10 -> 15 | F136: =E136*'Portfólio — Margem Real'!$C$5 -> 87
A137: KPV | B137: KP5 | C137: 5mg | D137: 45 | E137: =D137/10 -> 4.5 | F137: =E137*'Portfólio — Margem Real'!$C$5 -> 26.1
A138: KPV | B138: KP10 | C138: 10mg | D138: 65 | E138: =D138/10 -> 6.5 | F138: =E138*'Portfólio — Margem Real'!$C$5 -> 37.7
A139: PE 22-28 | B139: PE10 | C139: 10mg | D139: 100 | E139: =D139/10 -> 10 | F139: =E139*'Portfólio — Margem Real'!$C$5 -> 58
A140: N-Acetyl Epitalon Amidate | B140: NET5 | C140: 5mg | D140: 80 | E140: =D140/10 -> 8 | F140: =E140*'Portfólio — Margem Real'!$C$5 -> 46.4
A141: BPC+GHK+TB500+KPV Blend | B141: KL80 | C141: 80mg | D141: 190 | E141: =D141/10 -> 19 | F141: =E141*'Portfólio — Margem Real'!$C$5 -> 110.2
A142: Liraglutide | B142: LL5 | C142: 5mg | D142: 75 | E142: =D142/10 -> 7.5 | F142: =E142*'Portfólio — Margem Real'!$C$5 -> 43.5
A143: Liraglutide | B143: LL10 | C143: 10mg | D143: 120 | E143: =D143/10 -> 12 | F143: =E143*'Portfólio — Margem Real'!$C$5 -> 69.6
... A148: Acetic acid water | B148: AA03 | C148: 3ML | D148: 10 | E148: =D148/10 -> 1 | F148: =E148*'Portfólio — Margem Real'!$C$5 -> 5.8
